matomo_api/__init__.py
matomo_api/decorators.py
matomo_api/module_methods.py
matomo_api/parameter_specifications.py
matomo_api-1.0b5.dist-info/LICENSE
matomo_api-1.0b5.dist-info/METADATA
matomo_api-1.0b5.dist-info/WHEEL
matomo_api-1.0b5.dist-info/top_level.txt
matomo_api-1.0b5.dist-info/RECORD
