Metadata-Version: 2.1
Name: matomo-api
Version: 1.0b5
Summary: Python wrapper for the Matomo reporting API
Home-page: UNKNOWN
Author: Zjoz Deep
Author-email: zjozdeep@gmail.com
License: UNKNOWN
Platform: UNKNOWN
Classifier: Development Status :: 4 - Beta
Classifier: Programming Language :: Python :: 3.9
Classifier: License :: OSI Approved :: GNU General Public License v3 or later (GPLv3+)
Classifier: Operating System :: OS Independent
Requires-Python: >=3.9
License-File: LICENSE
